pacco/__init__.py
pacco/cli/__init__.py
pacco/cli/entry_point.py
pacco/cli/test_utils.py
pacco/cli/tests.py
pacco/cli/commands/__init__.py
pacco/cli/commands/binary.py
pacco/cli/commands/pacco.py
pacco/cli/commands/registry.py
pacco/cli/commands/remote.py
pacco/cli/commands/utils/__init__.py
pacco/cli/commands/utils/command_abstract.py
pacco/cli/commands/utils/output_stream.py
pacco/manager/__init__.py
pacco/manager/remote_manager.py
pacco/manager/abstracts/__init__.py
pacco/manager/abstracts/binary_factory.py
pacco/manager/abstracts/package_binary.py
pacco/manager/abstracts/package_registry.py
pacco/manager/abstracts/registry_factory.py
pacco/manager/abstracts/remote.py
pacco/manager/abstracts/remote_factory.py
pacco/manager/file_based/__init__.py
pacco/manager/file_based/package_binary.py
pacco/manager/file_based/package_registry.py
pacco/manager/file_based/remote.py
pacco/manager/file_based/utils/__init__.py
pacco/manager/file_based/utils/clients/__init__.py
pacco/manager/file_based/utils/clients/abstract.py
pacco/manager/file_based/utils/clients/client_factory.py
pacco/manager/file_based/utils/clients/helper.py
pacco/manager/file_based/utils/clients/local.py
pacco/manager/file_based/utils/clients/nexus.py
pacco/manager/file_based/utils/clients/nexus3.py
pacco/manager/file_based/utils/clients/test_client.py
pacco/manager/file_based/utils/clients/webdav.py
pacco/manager/utils/__init__.py
pacco/manager/utils/cache.py
pacco/manager/utils/clients.py
pacco-0.4.3.dist-info/LICENSE
pacco-0.4.3.dist-info/METADATA
pacco-0.4.3.dist-info/WHEEL
pacco-0.4.3.dist-info/entry_points.txt
pacco-0.4.3.dist-info/top_level.txt
pacco-0.4.3.dist-info/RECORD
