Metadata-Version: 2.1
Name: pacco
Version: 0.4.3
Summary: A simple package manager (used for prebuilt binary), interoperable with Nexus repository manager
Home-page: https://kwinata.github.io/pacco/
Author: Kevin Winata
Author-email: kevinwinatamichael@gmail.com
License: UNKNOWN
Platform: UNKNOWN
Requires-Python: >=3.7
Requires-Dist: requests
Requires-Dist: beautifulsoup4
Requires-Dist: PyYAML
